{
  "template": "tweets-*",
  "settings": {},
  "mappings": {
    "avocado": {
      "properties": {
        "coordinates": {
          "properties": {
            "coordinates": {
              "type": "geo_point",
              "ignore_malformed": true
            }
          }
        },
        "geo": {
          "properties": {
            "coordinates": {
              "type": "geo_point",
              "ignore_malformed": true
            }
          }
        },
        "text": {
          "type": "text",
          "fields": {
            "keyword": {
              "type": "keyword"
            },
            "stop_analyzed": {
              "type": "text",
              "analyzer": "stop",
              "fielddata": true
            }
          }
        }
      }
    }
  }
}
